{
  "id": "colony-1_093",
  "winrate": 70.9,
  "trades": 182,
  "pnl": 6157,
  "params": {
    "rr_ratio": 3,
    "lookback_fast": 2,
    "lookback_slow": 11,
    "entry_threshold": 0.0019,
    "atr_mult": 0.92
  },
  "fitness": 2.2688,
  "saved_at": "2026-06-17T14:52:11.735347",
  "recent_mistakes": [
    "SL: stopped out",
    "SL: stopped out",
    "reversed after entry",
    "SL: stopped out",
    "reversed after entry",
    "SL: stopped out",
    "SL: stopped out",
    "SL: stopped out"
  ]
}